python_conex_top/__init__.py
python_conex_top/python_conex.py
python_conex_top-0.0.1.dist-info/METADATA
python_conex_top-0.0.1.dist-info/WHEEL
python_conex_top-0.0.1.dist-info/RECORD
